setup.py
Oneiroi_Client.egg-info/PKG-INFO
Oneiroi_Client.egg-info/SOURCES.txt
Oneiroi_Client.egg-info/dependency_links.txt
Oneiroi_Client.egg-info/requires.txt
Oneiroi_Client.egg-info/top_level.txt
becosOneiroi/__init__.py
becosOneiroi/becosOneiroi.py