Metadata-Version: 1.1
Name: Oneiroi-Client
Version: 2.0.0.10
Summary: Provides the basic functionality to communincat with Oneiroi 2.0 Daemon
Home-page: UNKNOWN
Author: Waqas Ahmed
Author-email: waqas.ahmed@becos.de
License: Apache
Keywords: Oneiroi,becos
Platform: UNKNOWN
Classifier: Programming Language :: Python :: 3.6
